{"Metadata":{"WriteTimestampMicros":{"N":"1716791050804459"}},"Keys":{"name":{"S":"Solstice411"}},"OldImage":{"activities":{"L":[{"M":{"activity":{"S":"Listen to music"},"timestamp":{"S":"Sat, 04 May 2024 04:54:56 GMT"}}}]},"name":{"S":"Solstice411"}},"NewImage":{"activities":{"L":[{"M":{"activity":{"S":"Listen to music"},"timestamp":{"S":"Sat, 04 May 2024 04:54:56 GMT"}}},{"M":{"activity":{"S":"Play violin"},"timestamp":{"S":"Mon, 27 May 2024 06:24:10 GMT"}}}]},"name":{"S":"Solstice411"}}}
{"Metadata":{"WriteTimestampMicros":{"N":"1716791110709290"}},"Keys":{"name":{"S":"Chant502"}},"OldImage":{"activities":{"L":[{"M":{"activity":{"S":"Studying english"},"timestamp":{"S":"Sun, 31 Mar 2024 15:37:10 GMT"}}},{"M":{"activity":{"S":"Studying science"},"timestamp":{"S":"Sun, 14 Apr 2024 02:15:18 GMT"}}},{"M":{"activity":{"S":"Play with pet rocks"},"timestamp":{"S":"Sun, 14 Apr 2024 02:17:07 GMT"}}},{"M":{"activity":{"S":"Studying science"},"timestamp":{"S":"Sun, 14 Apr 2024 02:18:35 GMT"}}},{"M":{"activity":{"S":"Studying science"},"timestamp":{"S":"Sun, 14 Apr 2024 02:23:24 GMT"}}},{"M":{"activity":{"S":"Listen to music"},"timestamp":{"S":"Sun, 14 Apr 2024 02:24:42 GMT"}}},{"M":{"activity":{"S":"Went to sleep"},"timestamp":{"S":"Sun, 21 Apr 2024 15:19:30 GMT"}}},{"M":{"activity":{"S":"Watch TV"},"timestamp":{"S":"Sun, 21 Apr 2024 15:21:25 GMT"}}},{"M":{"activity":{"S":"Play violin"},"timestamp":{"S":"Sun, 21 Apr 2024 15:22:10 GMT"}}},{"M":{"activity":{"S":"Born"},"timestamp":{"S":"Sun, 21 Apr 2024 15:23:57 GMT"}}},{"M":{"activity":{"S":"Studying english"},"timestamp":{"S":"Sun, 21 Apr 2024 15:24:19 GMT"}}},{"M":{"activity":{"S":"Play violin"},"timestamp":{"S":"Sat, 04 May 2024 04:20:27 GMT"}}},{"M":{"activity":{"S":"Born"},"timestamp":{"S":"Sat, 04 May 2024 04:23:08 GMT"}}},{"M":{"activity":{"S":"Studying maths"},"timestamp":{"S":"Sat, 04 May 2024 04:25:51 GMT"}}},{"M":{"activity":{"S":"Eat hotdogs"},"timestamp":{"S":"Sat, 04 May 2024 04:29:19 GMT"}}},{"M":{"activity":{"S":"Listen to music"},"timestamp":{"S":"Sat, 04 May 2024 04:29:41 GMT"}}},{"M":{"activity":{"S":"Went to school"},"timestamp":{"S":"Sat, 04 May 2024 04:29:48 GMT"}}},{"M":{"activity":{"S":"Studying science"},"timestamp":{"S":"Sat, 04 May 2024 04:29:49 GMT"}}},{"M":{"activity":{"S":"Listen to music"},"timestamp":{"S":"Sat, 04 May 2024 04:31:14 GMT"}}},{"M":{"activity":{"S":"Brush teeth"},"timestamp":{"S":"Sat, 04 May 2024 04:45:25 GMT"}}},{"M":{"activity":{"S":"Play with pet rocks"},"timestamp":{"S":"Sat, 04 May 2024 04:47:04 GMT"}}},{"M":{"activity":{"S":"Watch TV"},"timestamp":{"S":"Sat, 04 May 2024 04:47:37 GMT"}}},{"M":{"activity":{"S":"Play with pet rocks"},"timestamp":{"S":"Sat, 04 May 2024 04:48:59 GMT"}}},{"M":{"activity":{"S":"Went to sleep"},"timestamp":{"S":"Sat, 04 May 2024 04:49:41 GMT"}}},{"M":{"activity":{"S":"Play with pet rocks"},"timestamp":{"S":"Sat, 04 May 2024 04:50:05 GMT"}}},{"M":{"activity":{"S":"Brush teeth"},"timestamp":{"S":"Sat, 04 May 2024 04:51:28 GMT"}}},{"M":{"activity":{"S":"Play with pet rocks"},"timestamp":{"S":"Sat, 04 May 2024 05:20:34 GMT"}}},{"M":{"activity":{"S":"Came home"},"timestamp":{"S":"Sat, 04 May 2024 05:21:40 GMT"}}},{"M":{"activity":{"S":"Watch TV"},"timestamp":{"S":"Sat, 04 May 2024 05:40:08 GMT"}}},{"M":{"activity":{"S":"Went to sleep"},"timestamp":{"S":"Thu, 23 May 2024 13:55:10 GMT"}}}]},"name":{"S":"Chant502"}},"NewImage":{"activities":{"L":[{"M":{"activity":{"S":"Studying english"},"timestamp":{"S":"Sun, 31 Mar 2024 15:37:10 GMT"}}},{"M":{"activity":{"S":"Studying science"},"timestamp":{"S":"Sun, 14 Apr 2024 02:15:18 GMT"}}},{"M":{"activity":{"S":"Play with pet rocks"},"timestamp":{"S":"Sun, 14 Apr 2024 02:17:07 GMT"}}},{"M":{"activity":{"S":"Studying science"},"timestamp":{"S":"Sun, 14 Apr 2024 02:18:35 GMT"}}},{"M":{"activity":{"S":"Studying science"},"timestamp":{"S":"Sun, 14 Apr 2024 02:23:24 GMT"}}},{"M":{"activity":{"S":"Listen to music"},"timestamp":{"S":"Sun, 14 Apr 2024 02:24:42 GMT"}}},{"M":{"activity":{"S":"Went to sleep"},"timestamp":{"S":"Sun, 21 Apr 2024 15:19:30 GMT"}}},{"M":{"activity":{"S":"Watch TV"},"timestamp":{"S":"Sun, 21 Apr 2024 15:21:25 GMT"}}},{"M":{"activity":{"S":"Play violin"},"timestamp":{"S":"Sun, 21 Apr 2024 15:22:10 GMT"}}},{"M":{"activity":{"S":"Born"},"timestamp":{"S":"Sun, 21 Apr 2024 15:23:57 GMT"}}},{"M":{"activity":{"S":"Studying english"},"timestamp":{"S":"Sun, 21 Apr 2024 15:24:19 GMT"}}},{"M":{"activity":{"S":"Play violin"},"timestamp":{"S":"Sat, 04 May 2024 04:20:27 GMT"}}},{"M":{"activity":{"S":"Born"},"timestamp":{"S":"Sat, 04 May 2024 04:23:08 GMT"}}},{"M":{"activity":{"S":"Studying maths"},"timestamp":{"S":"Sat, 04 May 2024 04:25:51 GMT"}}},{"M":{"activity":{"S":"Eat hotdogs"},"timestamp":{"S":"Sat, 04 May 2024 04:29:19 GMT"}}},{"M":{"activity":{"S":"Listen to music"},"timestamp":{"S":"Sat, 04 May 2024 04:29:41 GMT"}}},{"M":{"activity":{"S":"Went to school"},"timestamp":{"S":"Sat, 04 May 2024 04:29:48 GMT"}}},{"M":{"activity":{"S":"Studying science"},"timestamp":{"S":"Sat, 04 May 2024 04:29:49 GMT"}}},{"M":{"activity":{"S":"Listen to music"},"timestamp":{"S":"Sat, 04 May 2024 04:31:14 GMT"}}},{"M":{"activity":{"S":"Brush teeth"},"timestamp":{"S":"Sat, 04 May 2024 04:45:25 GMT"}}},{"M":{"activity":{"S":"Play with pet rocks"},"timestamp":{"S":"Sat, 04 May 2024 04:47:04 GMT"}}},{"M":{"activity":{"S":"Watch TV"},"timestamp":{"S":"Sat, 04 May 2024 04:47:37 GMT"}}},{"M":{"activity":{"S":"Play with pet rocks"},"timestamp":{"S":"Sat, 04 May 2024 04:48:59 GMT"}}},{"M":{"activity":{"S":"Went to sleep"},"timestamp":{"S":"Sat, 04 May 2024 04:49:41 GMT"}}},{"M":{"activity":{"S":"Play with pet rocks"},"timestamp":{"S":"Sat, 04 May 2024 04:50:05 GMT"}}},{"M":{"activity":{"S":"Brush teeth"},"timestamp":{"S":"Sat, 04 May 2024 04:51:28 GMT"}}},{"M":{"activity":{"S":"Play with pet rocks"},"timestamp":{"S":"Sat, 04 May 2024 05:20:34 GMT"}}},{"M":{"activity":{"S":"Came home"},"timestamp":{"S":"Sat, 04 May 2024 05:21:40 GMT"}}},{"M":{"activity":{"S":"Watch TV"},"timestamp":{"S":"Sat, 04 May 2024 05:40:08 GMT"}}},{"M":{"activity":{"S":"Went to sleep"},"timestamp":{"S":"Thu, 23 May 2024 13:55:10 GMT"}}},{"M":{"activity":{"S":"Came home"},"timestamp":{"S":"Mon, 27 May 2024 06:25:10 GMT"}}}]},"name":{"S":"Chant502"}}}
{"Metadata":{"WriteTimestampMicros":{"N":"1716790450778514"}},"Keys":{"name":{"S":"Chant3756"}},"OldImage":{"activities":{"L":[{"M":{"activity":{"S":"Born"},"timestamp":{"S":"Sat, 04 May 2024 04:47:44 GMT"}}},{"M":{"activity":{"S":"Came home"},"timestamp":{"S":"Sat, 04 May 2024 04:49:01 GMT"}}},{"M":{"activity":{"S":"Play with pet rocks"},"timestamp":{"S":"Sat, 04 May 2024 04:51:11 GMT"}}},{"M":{"activity":{"S":"Went to sleep"},"timestamp":{"S":"Sat, 04 May 2024 04:52:14 GMT"}}},{"M":{"activity":{"S":"Brush teeth"},"timestamp":{"S":"Sat, 04 May 2024 05:19:55 GMT"}}},{"M":{"activity":{"S":"Studying maths"},"timestamp":{"S":"Sat, 04 May 2024 05:20:08 GMT"}}},{"M":{"activity":{"S":"Play with pet rocks"},"timestamp":{"S":"Sat, 04 May 2024 05:23:44 GMT"}}}]},"name":{"S":"Chant3756"}}}
{"Metadata":{"WriteTimestampMicros":{"N":"1716790870763105"}},"Keys":{"name":{"S":"Chant9905"}},"OldImage":{"activities":{"L":[{"M":{"activity":{"S":"Studying english"},"timestamp":{"S":"Sat, 04 May 2024 04:48:58 GMT"}}},{"M":{"activity":{"S":"Studying maths"},"timestamp":{"S":"Sat, 04 May 2024 04:50:12 GMT"}}},{"M":{"activity":{"S":"Born"},"timestamp":{"S":"Sat, 04 May 2024 04:52:28 GMT"}}},{"M":{"activity":{"S":"Studying science"},"timestamp":{"S":"Sat, 04 May 2024 04:53:23 GMT"}}},{"M":{"activity":{"S":"Studying maths"},"timestamp":{"S":"Sat, 04 May 2024 05:21:33 GMT"}}},{"M":{"activity":{"S":"Born"},"timestamp":{"S":"Sat, 04 May 2024 05:23:19 GMT"}}},{"M":{"activity":{"S":"Went to sleep"},"timestamp":{"S":"Sat, 04 May 2024 05:23:50 GMT"}}}]},"name":{"S":"Chant9905"}}}
{"Metadata":{"WriteTimestampMicros":{"N":"1716790330795390"}},"Keys":{"name":{"S":"Olwen779"}},"OldImage":{"activities":{"L":[{"M":{"activity":{"S":"Brush teeth"},"timestamp":{"S":"Sat, 04 May 2024 04:35:19 GMT"}}},{"M":{"activity":{"S":"Went to sleep"},"timestamp":{"S":"Sat, 04 May 2024 04:46:13 GMT"}}},{"M":{"activity":{"S":"Eat hotdogs"},"timestamp":{"S":"Sat, 04 May 2024 04:55:29 GMT"}}},{"M":{"activity":{"S":"Studying science"},"timestamp":{"S":"Sat, 04 May 2024 05:21:32 GMT"}}},{"M":{"activity":{"S":"Play with pet rocks"},"timestamp":{"S":"Sat, 04 May 2024 05:23:22 GMT"}}}]},"name":{"S":"Olwen779"}}}
{"Metadata":{"WriteTimestampMicros":{"N":"1716790570759421"}},"Keys":{"name":{"S":"Argyros6879"}},"OldImage":{"activities":{"L":[{"M":{"activity":{"S":"Listen to music"},"timestamp":{"S":"Sat, 04 May 2024 05:21:47 GMT"}}},{"M":{"activity":{"S":"Studying maths"},"timestamp":{"S":"Sat, 04 May 2024 05:57:11 GMT"}}}]},"name":{"S":"Argyros6879"}}}
{"Metadata":{"WriteTimestampMicros":{"N":"1716790690742041"}},"Keys":{"name":{"S":"Elmas1274"}},"OldImage":{"activities":{"L":[{"M":{"activity":{"S":"Born"},"timestamp":{"S":"Sun, 14 Apr 2024 02:15:06 GMT"}}},{"M":{"activity":{"S":"Play with pet rocks"},"timestamp":{"S":"Sun, 14 Apr 2024 02:18:07 GMT"}}},{"M":{"activity":{"S":"Went to school"},"timestamp":{"S":"Sun, 14 Apr 2024 02:19:56 GMT"}}},{"M":{"activity":{"S":"Went to school"},"timestamp":{"S":"Sat, 04 May 2024 04:26:26 GMT"}}},{"M":{"activity":{"S":"Studying maths"},"timestamp":{"S":"Sat, 04 May 2024 04:27:44 GMT"}}},{"M":{"activity":{"S":"Studying science"},"timestamp":{"S":"Sat, 04 May 2024 04:30:44 GMT"}}},{"M":{"activity":{"S":"Eat hotdogs"},"timestamp":{"S":"Sat, 04 May 2024 04:37:04 GMT"}}},{"M":{"activity":{"S":"Watch TV"},"timestamp":{"S":"Sat, 04 May 2024 04:44:15 GMT"}}},{"M":{"activity":{"S":"Listen to music"},"timestamp":{"S":"Sat, 04 May 2024 04:44:48 GMT"}}},{"M":{"activity":{"S":"Watch TV"},"timestamp":{"S":"Sat, 04 May 2024 04:51:50 GMT"}}},{"M":{"activity":{"S":"Studying maths"},"timestamp":{"S":"Sat, 04 May 2024 04:54:35 GMT"}}},{"M":{"activity":{"S":"Listen to music"},"timestamp":{"S":"Sat, 04 May 2024 04:55:51 GMT"}}},{"M":{"activity":{"S":"Eat hotdogs"},"timestamp":{"S":"Sat, 04 May 2024 05:20:17 GMT"}}}]},"name":{"S":"Elmas1274"}},"NewImage":{"activities":{"L":[{"M":{"activity":{"S":"Born"},"timestamp":{"S":"Sun, 14 Apr 2024 02:15:06 GMT"}}},{"M":{"activity":{"S":"Play with pet rocks"},"timestamp":{"S":"Sun, 14 Apr 2024 02:18:07 GMT"}}},{"M":{"activity":{"S":"Went to school"},"timestamp":{"S":"Sun, 14 Apr 2024 02:19:56 GMT"}}},{"M":{"activity":{"S":"Went to school"},"timestamp":{"S":"Sat, 04 May 2024 04:26:26 GMT"}}},{"M":{"activity":{"S":"Studying maths"},"timestamp":{"S":"Sat, 04 May 2024 04:27:44 GMT"}}},{"M":{"activity":{"S":"Studying science"},"timestamp":{"S":"Sat, 04 May 2024 04:30:44 GMT"}}},{"M":{"activity":{"S":"Eat hotdogs"},"timestamp":{"S":"Sat, 04 May 2024 04:37:04 GMT"}}},{"M":{"activity":{"S":"Watch TV"},"timestamp":{"S":"Sat, 04 May 2024 04:44:15 GMT"}}},{"M":{"activity":{"S":"Listen to music"},"timestamp":{"S":"Sat, 04 May 2024 04:44:48 GMT"}}},{"M":{"activity":{"S":"Watch TV"},"timestamp":{"S":"Sat, 04 May 2024 04:51:50 GMT"}}},{"M":{"activity":{"S":"Studying maths"},"timestamp":{"S":"Sat, 04 May 2024 04:54:35 GMT"}}},{"M":{"activity":{"S":"Listen to music"},"timestamp":{"S":"Sat, 04 May 2024 04:55:51 GMT"}}},{"M":{"activity":{"S":"Eat hotdogs"},"timestamp":{"S":"Sat, 04 May 2024 05:20:17 GMT"}}},{"M":{"activity":{"S":"Watch TV"},"timestamp":{"S":"Mon, 27 May 2024 06:18:10 GMT"}}}]},"name":{"S":"Elmas1274"}}}
